bin/kalki.py
kalki/__init__.py
kalki/create_app.py
kalki/kalkiminify.py
kalki/service.py
kalki/minify/__init__.py
kalki/minify/minify.py
kalki/minify/minify_logic.py
kalki/services/__init__.py
kalki/services/compile.py
kalki/services/global_var.py
kalki/startapps/__init__.py
kalki/startapps/main.py
kalki-0.1.8.dist-info/LICENSE
kalki-0.1.8.dist-info/METADATA
kalki-0.1.8.dist-info/WHEEL
kalki-0.1.8.dist-info/entry_points.txt
kalki-0.1.8.dist-info/top_level.txt
kalki-0.1.8.dist-info/RECORD
