Metadata-Version: 2.1
Name: kalki
Version: 0.1.8
Summary: Kalki is a library to create dynamic CSS
Home-page: https://github.com/biswajitbimoli/kalki
Author: Biswajit Bimoli
Author-email: biswajitbimoli@gmail.com
Classifier: Development Status :: 4 - Beta
Classifier: Intended Audience :: Developers
Classifier: License :: OSI Approved :: MIT License
Classifier: Operating System :: OS Independent
Classifier: Programming Language :: Python
Classifier: Topic :: Software Development :: Libraries
License-File: LICENSE
